doc/_api.rst
doc/conf.py
doc/index.rst
doc/quickstart.md
doc/_templates/custom-module-template.rst
doc/developer_guide/developing_lewis.md
doc/developer_guide/framework_details.md
doc/developer_guide/release_checklist.md
doc/developer_guide/writing_devices.md
doc/release_notes/release_1_0_0.md
doc/release_notes/release_1_0_1.md
doc/release_notes/release_1_0_2.md
doc/release_notes/release_1_0_3.md
doc/release_notes/release_1_1_0.md
doc/release_notes/release_1_1_1.md
doc/release_notes/release_1_2_0.md
doc/release_notes/release_1_2_1.md
doc/release_notes/release_1_2_2.md
doc/release_notes/release_1_3_0.md
doc/release_notes/release_1_3_1.md
doc/release_notes/release_1_3_2.md
doc/release_notes/release_1_3_3.md
doc/release_notes/release_notes.rst
doc/resources/diagrams/SimulationCycles.png
doc/resources/diagrams/SimulationCycles.xml
doc/resources/diagrams/chopper.fsm
doc/resources/logo/lewis-logo-simple.png
doc/resources/logo/lewis-logo-simple.svg
doc/resources/logo/lewis-logo.png
doc/resources/logo/lewis-logo.svg
doc/user_guide/adapter_specifics.md
doc/user_guide/command_line_tools.md
doc/user_guide/remote_access_devices.md
doc/user_guide/remote_access_simulation.md
doc/user_guide/usage_with_python.md
lewis/__init__.py
lewis/__main__.py
lewis/_version.py
lewis/adapters/__init__.py
lewis/adapters/epics.py
lewis/adapters/modbus.py
lewis/adapters/stream.py
lewis/core/__init__.py
lewis/core/adapters.py
lewis/core/approaches.py
lewis/core/control_client.py
lewis/core/control_server.py
lewis/core/devices.py
lewis/core/exceptions.py
lewis/core/logging.py
lewis/core/processor.py
lewis/core/simulation.py
lewis/core/statemachine.py
lewis/core/utils.py
lewis/devices/__init__.py
lewis/devices/chopper/__init__.py
lewis/devices/chopper/devices/__init__.py
lewis/devices/chopper/devices/bearings.py
lewis/devices/chopper/devices/device.py
lewis/devices/chopper/devices/states.py
lewis/devices/chopper/interfaces/__init__.py
lewis/devices/chopper/interfaces/epics_interface.py
lewis-1.3.5.dist-info/LICENSE
lewis-1.3.5.dist-info/METADATA
lewis-1.3.5.dist-info/WHEEL
lewis-1.3.5.dist-info/entry_points.txt
lewis-1.3.5.dist-info/top_level.txt
lewis-1.3.5.dist-info/RECORD
