Metadata-Version: 2.2
Name: lewis
Version: 1.3.5
Summary: Lewis - Let's write intricate simulators!
Author: ScreamingUdder
Author-email: ISIS Experiment Controls <ISISExperimentControls@stfc.ac.uk>
License:                     GNU GENERAL PUBLIC LICENSE
Project-URL: Homepage, https://github.com/ISISComputingGroup/lewis
Project-URL: Bug Reports, https://github.com/ISISComputingGroup/lewis/issues
Project-URL: Source, https://github.com/ISISComputingGroup/lewis
Keywords: hardware,controls,epics,simulation
Classifier: Development Status :: 5 - Production/Stable
Classifier: Environment :: Console
Classifier: Intended Audience :: Developers
Classifier: Intended Audience :: Science/Research
Classifier: Topic :: Scientific/Engineering
Classifier: Topic :: Software Development :: Libraries
Classifier: License :: OSI Approved :: GNU General Public License v3 or later (GPLv3+)
Classifier: Operating System :: OS Independent
Classifier: Programming Language :: Python :: 3
Requires-Python: >=3.10
License-File: LICENSE
Requires-Dist: pyzmq
Requires-Dist: json-rpc
Requires-Dist: semantic_version
Requires-Dist: PyYAML
Requires-Dist: scanf
Requires-Dist: pyasynchat; python_version >= "3.12"
Provides-Extra: epics
Requires-Dist: pcaspy; extra == "epics"
Provides-Extra: doc
Requires-Dist: sphinx; extra == "doc"
Requires-Dist: sphinx_rtd_theme; extra == "doc"
Requires-Dist: myst_parser; extra == "doc"
Requires-Dist: sphinx-autobuild; extra == "doc"
Provides-Extra: dev
Requires-Dist: parameterized; extra == "dev"
Requires-Dist: lewis[doc]; extra == "dev"
Requires-Dist: pytest; extra == "dev"
Requires-Dist: pytest-cov; extra == "dev"
Requires-Dist: coverage; extra == "dev"
Requires-Dist: tox; extra == "dev"
Requires-Dist: approvaltests; extra == "dev"
Requires-Dist: pytest-approvaltests; extra == "dev"
Requires-Dist: ruff; extra == "dev"
Requires-Dist: pyright; extra == "dev"
